.DS_Store
label_maker/__init__.py
label_maker/countries.txt
label_maker/download.py
label_maker/filter.py
label_maker/images.py
label_maker/label.py
label_maker/main.py
label_maker/package.py
label_maker/palette.py
label_maker/plot_utils.py
label_maker/preview.py
label_maker/stream_filter.py
label_maker/utils.py
label_maker/validate.py
label_maker/version.py
label_maker/utils/__init__.py
label_maker/utils/cli_utils.py
label_maker/utils/plot_utils.py
test/__init__.py
test/test_filter.py
test/test_label.py
test/test_utils.py
test/test_validate.py
test/verify-labels.py
test/verify-package.py
test/unit/__init__.py
test/unit/test_filter.py
test/unit/test_label.py
test/unit/test_utils.py
test/unit/test_validate.py
label_maker-0.7.0.dist-info/LICENSE.txt
label_maker-0.7.0.dist-info/METADATA
label_maker-0.7.0.dist-info/WHEEL
label_maker-0.7.0.dist-info/dependency_links.txt
label_maker-0.7.0.dist-info/entry_points.txt
label_maker-0.7.0.dist-info/top_level.txt
label_maker-0.7.0.dist-info/RECORD
