Metadata-Version: 2.1
Name: label-maker
Version: 0.7.0
Summary: Data preparation for satellite machine learning
Home-page: https://github.com/developmentseed/label-maker/
Author: Drew Bollinger
Author-email: drew@developmentseed.org
License: MIT
Platform: UNKNOWN
Classifier: Intended Audience :: Developers
Classifier: License :: OSI Approved :: MIT License
Classifier: Programming Language :: Python :: 3.6
Requires-Dist: Cerberus (==1.1)
Requires-Dist: click (==6.7)
Requires-Dist: geojson (==2.3.0)
Requires-Dist: homura (==0.1.5)
Requires-Dist: humanize (==0.5.1)
Requires-Dist: mapbox-vector-tile (==1.2.0)
Requires-Dist: mbutil (==0.3.0)
Requires-Dist: mercantile (==1.0.0)
Requires-Dist: numpy (==1.13.3)
Requires-Dist: olefile (==0.44)
Requires-Dist: Pillow (==4.3.0)
Requires-Dist: protobuf (==3.5.0.post1)
Requires-Dist: pyclipper (==1.0.6)
Requires-Dist: pycurl (==7.43.0.1)
Requires-Dist: pyproj (==1.9.5.1)
Requires-Dist: rasterio[s3] (==1.0a12)
Requires-Dist: requests (>=2.20.0)
Requires-Dist: Shapely (>=1.6.3)
Requires-Dist: six (==1.10.0)
Requires-Dist: tilepie (==0.2.1)
